squealer/__init__.py
squealer/sql_table_tools.py
squealer/sqlite_session.py
squealer/utilities/__init__.py
squealer-0.5.5.dist-info/LICENSE
squealer-0.5.5.dist-info/METADATA
squealer-0.5.5.dist-info/WHEEL
squealer-0.5.5.dist-info/top_level.txt
squealer-0.5.5.dist-info/RECORD
