Metadata-Version: 2.1
Name: squealer
Version: 0.5.5
Summary: Another sqlite wrapper
Home-page: https://github.com/andressl91/squealer
Author: jackal
Author-email: pep8@pm.me
License: MIT license
Keywords: sqlite sqlite3 development
Platform: UNKNOWN
Classifier: Development Status :: 2 - Pre-Alpha
Classifier: Intended Audience :: Developers
Classifier: License :: OSI Approved :: MIT License
Classifier: Natural Language :: English
Classifier: Programming Language :: Python :: 3.7
